Metadata-Version: 2.1
Name: jk-furl
Version: 0.2021.3.15
Summary: This python module offers support for URL handling. It provides the existing furl implementation as well as some additional features.
Home-page: UNKNOWN
Author: Jürgen Knauth
Author-email: pubsrc@binary-overflow.de
License: Apache2
Keywords: url,www,html
Platform: UNKNOWN
Classifier: Development Status :: 5 - Production/Stable
Classifier: License :: OSI Approved :: Apache Software License
Classifier: Programming Language :: Python :: 3
